MANIFEST.in
README.md
setup.cfg
setup.py
pyramid_rest_route/__init__.py
pyramid_rest_route/route.py
pyramid_rest_route/view.py
pyramid_rest_route.egg-info/PKG-INFO
pyramid_rest_route.egg-info/SOURCES.txt
pyramid_rest_route.egg-info/dependency_links.txt
pyramid_rest_route.egg-info/top_level.txt