Metadata-Version: 1.1
Name: pyramid-rest-route
Version: 0.2
Summary: Simple helper for creating rest route and view
Home-page: https://github.com/rickmak/pyramid_rest_route
Author: Rick Mak
Author-email: rick.mak@gmail.com
License: MIT
Platform: UNKNOWN
Classifier: License :: OSI Approved :: MIT License
Classifier: Intended Audience :: Developers
Classifier: Programming Language :: Python :: 2
Classifier: Programming Language :: Python :: 2.7
Classifier: Programming Language :: Python :: 3
Classifier: Programming Language :: Python :: 3.3
Classifier: Programming Language :: Python :: 3.4
Classifier: Operating System :: POSIX
Classifier: Operating System :: MacOS :: MacOS X
Classifier: Environment :: Web Environment
Classifier: Development Status :: 3 - Alpha
